pynodewidget/__init__.py
pynodewidget/exceptions.py
pynodewidget/grid_layouts.py
pynodewidget/json_schema_node.py
pynodewidget/observable_dict.py
pynodewidget/protocols.py
pynodewidget/widget.py
pynodewidget/layout/__init__.py
pynodewidget/layout/grid_builder.py
pynodewidget/layout/presets.py
pynodewidget/models/__init__.py
pynodewidget/models/grid.py
pynodewidget/models/node.py
pynodewidget/models/components/__init__.py
pynodewidget/models/components/base.py
pynodewidget/models/components/fields.py
pynodewidget/models/components/handles.py
pynodewidget/models/components/layouts.py
pynodewidget/models/components/ui.py
pynodewidget/static/index.css
pynodewidget/static/index.js
pynodewidget/static/index.js.map
pynodewidget/static/json_schema_node_entry.css
pynodewidget/static/json_schema_node_entry.js
pynodewidget/static/json_schema_node_entry.js.map
pynodewidget/static/pynodewidget-js.css
pynodewidget/static/standalone.css
pynodewidget/static/standalone.iife.js
pynodewidget/templates/standalone.html.jinja2
pynodewidget-0.2.3.dist-info/METADATA
pynodewidget-0.2.3.dist-info/WHEEL
pynodewidget-0.2.3.dist-info/licenses/LICENSE
pynodewidget-0.2.3.dist-info/RECORD
