Metadata-Version: 2.4
Name: pynodewidget
Version: 0.2.3
Summary: A Python wrapper for ReactFlow using AnyWidget - build interactive node graphs without JavaScript
Project-URL: Homepage, https://henningscheufler.github.io/pynodewidget/
Project-URL: Issues, https://github.com/HenningScheufler/pynodewidget/issues
Author-email: Henning <henning.scheufler@web.de>
License-Expression: MIT
License-File: LICENSE
Keywords: graph,jupyter,nodes,reactflow,widget
Classifier: Framework :: Jupyter
Classifier: Intended Audience :: Developers
Classifier: Programming Language :: Python :: 3
Requires-Python: >=3.10
Requires-Dist: anywidget>=0.9.0
Requires-Dist: pydantic>=2.0.0
Requires-Dist: traitlets>=5.0.0
Provides-Extra: all
Requires-Dist: hatchling>=1.27.0; extra == 'all'
Requires-Dist: jupyterlab>=4.5.0; extra == 'all'
Requires-Dist: marimo>=0.18.0; extra == 'all'
Requires-Dist: mkdocs-material>=9.5.0; extra == 'all'
Requires-Dist: mkdocs>=1.6.0; extra == 'all'
Requires-Dist: mkdocstrings[python]>=0.25.0; extra == 'all'
Requires-Dist: mypy>=1.0.0; extra == 'all'
Requires-Dist: pymdown-extensions>=10.8.0; extra == 'all'
Requires-Dist: pytest-cov>=4.0.0; extra == 'all'
Requires-Dist: pytest>=7.0.0; extra == 'all'
Requires-Dist: pyyaml>=6.0.0; extra == 'all'
Requires-Dist: taskipy>=1.13.0; extra == 'all'
Provides-Extra: dev
Requires-Dist: hatchling>=1.27.0; extra == 'dev'
Requires-Dist: mypy>=1.0.0; extra == 'dev'
Requires-Dist: pytest-cov>=4.0.0; extra == 'dev'
Requires-Dist: pytest>=7.0.0; extra == 'dev'
Requires-Dist: taskipy>=1.13.0; extra == 'dev'
Provides-Extra: docs
Requires-Dist: mkdocs-material>=9.5.0; extra == 'docs'
Requires-Dist: mkdocs>=1.6.0; extra == 'docs'
Requires-Dist: mkdocstrings[python]>=0.25.0; extra == 'docs'
Requires-Dist: pymdown-extensions>=10.8.0; extra == 'docs'
Provides-Extra: notebooks
Requires-Dist: jupyterlab>=4.5.0; extra == 'notebooks'
Requires-Dist: marimo>=0.18.0; extra == 'notebooks'
